CHANGES.txt
LICENSE.txt
MANIFEST.in
README.txt
requirements.txt
setup.py
obelisk/__init__.py
obelisk/binary.py
obelisk/bitcoin.py
obelisk/bitset.py
obelisk/bittree.py
obelisk/client.py
obelisk/config.py
obelisk/deserialize.py
obelisk/error_code.py
obelisk/models.py
obelisk/numbertheory.py
obelisk/serialize.py
obelisk/transaction.py
obelisk/util.py
obelisk/zmq_fallback.py
obelisk/zmqbase.py
python_libbitcoinclient.egg-info/PKG-INFO
python_libbitcoinclient.egg-info/SOURCES.txt
python_libbitcoinclient.egg-info/dependency_links.txt
python_libbitcoinclient.egg-info/not-zip-safe
python_libbitcoinclient.egg-info/requires.txt
python_libbitcoinclient.egg-info/top_level.txt