Metadata-Version: 1.0
Name: python-libbitcoinclient
Version: 0.3.2
Summary: Python native client for the libbitcoin blockchain server.
Home-page: https://github.com/OpenBazaar/python-libbitcoinclient
Author: Chris Pacia
Author-email: chris@ob1.io
License: GNU Affero General Public License
Keywords: bitcoin blockchain libbitcoin query transaction federated
Platform: UNKNOWN
